viking/__init__.py
viking/__main__.py
viking/cli.py
viking/simulate.py
viking/translate.py
viking-1.0.4.dist-info/LICENSE
viking-1.0.4.dist-info/METADATA
viking-1.0.4.dist-info/WHEEL
viking-1.0.4.dist-info/entry_points.txt
viking-1.0.4.dist-info/top_level.txt
viking-1.0.4.dist-info/RECORD
